netlink/alchemy/__init__.py
netlink/alchemy/_integer.py
netlink_alchemy-0.0.2.dist-info/WHEEL
netlink_alchemy-0.0.2.dist-info/METADATA
netlink_alchemy-0.0.2.dist-info/RECORD
